MANIFEST.in
README.md
setup.cfg
setup.py
webnsock/__init__.py
webnsock/webnsock.py
webnsock.egg-info/PKG-INFO
webnsock.egg-info/SOURCES.txt
webnsock.egg-info/dependency_links.txt
webnsock.egg-info/entry_points.txt
webnsock.egg-info/not-zip-safe
webnsock.egg-info/requires.txt
webnsock.egg-info/top_level.txt
webnsock/www/base.html
webnsock/www/index.html
webnsock/www/webnsock/css/bootstrap-theme.css
webnsock/www/webnsock/css/bootstrap-theme.css.map
webnsock/www/webnsock/css/bootstrap-theme.min.css
webnsock/www/webnsock/css/bootstrap.css
webnsock/www/webnsock/css/bootstrap.css.map
webnsock/www/webnsock/css/bootstrap.min.css
webnsock/www/webnsock/fonts/glyphicons-halflings-regular.eot
webnsock/www/webnsock/fonts/glyphicons-halflings-regular.svg
webnsock/www/webnsock/fonts/glyphicons-halflings-regular.ttf
webnsock/www/webnsock/fonts/glyphicons-halflings-regular.woff
webnsock/www/webnsock/fonts/glyphicons-halflings-regular.woff2
webnsock/www/webnsock/js/autobahn.min.js
webnsock/www/webnsock/js/bootstrap.js
webnsock/www/webnsock/js/bootstrap.min.js
webnsock/www/webnsock/js/jquery.min.js
webnsock/www/webnsock/js/npm.js
webnsock/www/webnsock/js/reconnecting-websocket.min.js
webnsock/www/webnsock/js/webnsock.js