Metadata-Version: 1.1
Name: webnsock
Version: 0.0.4
Summary: A web.py and websocket framework for interactive webservices
Home-page: https://github.com/marc-hanheide/webnsock
Author: Marc Hanheide
Author-email: marc@hanheide.net
License: UNKNOWN
Download-URL: https://github.com/marc-hanheide/webnsock/archive/0.0.4.tar.gz
Keywords: web.py,websockets,webserver
Platform: UNKNOWN
